Talk/Encryption.py
Talk/__init__.py
Talk/Command/Commands.py
Talk/Command/__init__.py
Talk/GUI/Interface.py
Talk/GUI/__init__.py
Talk/NetObject/Client.py
Talk/NetObject/Connection.py
Talk/NetObject/Server.py
Talk/NetObject/Workers.py
Talk/NetObject/__init__.py
Talk/Objects/Data.py
Talk/Objects/Queue.py
Talk/Objects/__init__.py
Talk/Threading/Threading.py
Talk/Threading/__init__.py
STalk-0.0.4.dist-info/METADATA
STalk-0.0.4.dist-info/WHEEL
STalk-0.0.4.dist-info/top_level.txt
STalk-0.0.4.dist-info/RECORD
